tracking/__init__.py
tracking/sdk.py
python_tracking_sdk-0.0.1.dist-info/METADATA
python_tracking_sdk-0.0.1.dist-info/WHEEL
python_tracking_sdk-0.0.1.dist-info/top_level.txt
python_tracking_sdk-0.0.1.dist-info/RECORD
